papermill_report/__init__.py
papermill_report/__main__.py
papermill_report/_version.py
papermill_report/handlers.py
papermill_report/papermill_report.py
papermill_report/utils.py
papermill_report/static/js/jsoneditor.min.js
papermill_report/templates/error.html
papermill_report/templates/page.html
papermill_report/templates/report.html
papermill_report/tests/__init__.py
papermill_report/tests/conftest.py
papermill_report/tests/test_api.py
papermill_report/tests/test_configuration.py
papermill_report/tests/test_settings.py
papermill_report-2.0.5.dist-info/LICENSE
papermill_report-2.0.5.dist-info/METADATA
papermill_report-2.0.5.dist-info/WHEEL
papermill_report-2.0.5.dist-info/top_level.txt
papermill_report-2.0.5.dist-info/RECORD
