Metadata-Version: 2.1
Name: papermill-report
Version: 2.0.5
Summary: Microservice to generate Jupyter reports
Home-page: https://github.com/ariadnext/papermill_report
Author: ARIADNEXT
License: BSD-3-Clause
Keywords: papermill_report,papermill,jupyterhub,tornado
Platform: UNKNOWN
Classifier: Environment :: Console
Classifier: Intended Audience :: Developers
Classifier: Natural Language :: English
Classifier: License :: OSI Approved :: BSD License
Classifier: Programming Language :: Python
Classifier: Programming Language :: Python :: 3
Classifier: Programming Language :: Python :: 3.6
Classifier: Programming Language :: Python :: 3.7
Classifier: Programming Language :: Python :: 3.8
Classifier: Programming Language :: Python :: 3.9
Classifier: Programming Language :: Python :: Implementation :: CPython
Classifier: Programming Language :: Python :: Implementation :: PyPy
Classifier: Topic :: Software Development
Requires-Python: >=3.6
Requires-Dist: nbconvert
Requires-Dist: jinja2
Requires-Dist: papermill (>=2.2.0)
Requires-Dist: tornado (>=6)
Requires-Dist: traitlets (>=4)
Provides-Extra: dev
Requires-Dist: pip ; extra == 'dev'
Requires-Dist: wheel ; extra == 'dev'
Requires-Dist: black ; extra == 'dev'
Requires-Dist: flake8 ; extra == 'dev'
Requires-Dist: flake8-docstrings ; extra == 'dev'
Requires-Dist: flake8-blind-except ; extra == 'dev'
Requires-Dist: flake8-builtins ; extra == 'dev'
Requires-Dist: flake8-mutable ; extra == 'dev'
Requires-Dist: flake8-comprehensions ; extra == 'dev'
Requires-Dist: isort ; extra == 'dev'
Requires-Dist: jupyterhub (>=1) ; extra == 'dev'
Requires-Dist: rope ; extra == 'dev'
Requires-Dist: pytest ; extra == 'dev'
Requires-Dist: pytest-tornasync ; extra == 'dev'
Requires-Dist: ipykernel ; extra == 'dev'
